delcom904x/__init__.py
delcom904x/cli.py
delcom904x-0.5.0.dist-info/licenses/LICENSE
delcom904x-0.5.0.dist-info/METADATA
delcom904x-0.5.0.dist-info/WHEEL
delcom904x-0.5.0.dist-info/entry_points.txt
delcom904x-0.5.0.dist-info/top_level.txt
delcom904x-0.5.0.dist-info/RECORD
