Metadata-Version: 2.4
Name: delcom904x
Version: 0.5.0
Summary: A python module to control Delcom USBLMP Products 904x multi-color, USB, visual signal indicators
Author-email: Aaron Linville <aaron@linville.org>
License-Expression: ISC
Project-URL: Homepage, https://github.com/linville/delcom904x/
Project-URL: Changelog, https://github.com/linville/delcom904x/blob/main/CHANGELOG.md
Project-URL: Issues, https://github.com/linville/delcom904x/issues
Keywords: hidapi,usb-hid,iot-device
Classifier: Programming Language :: Python :: 3
Classifier: Operating System :: OS Independent
Classifier: Topic :: System :: Hardware :: Hardware Drivers
Classifier: Topic :: Home Automation
Classifier: Development Status :: 5 - Production/Stable
Requires-Python: >=3.9
License-File: LICENSE
Requires-Dist: hidapi==0.14.*
Provides-Extra: dev
Requires-Dist: black==25.1.*; extra == "dev"
Requires-Dist: build==1.2.*; extra == "dev"
Requires-Dist: ruff==0.11.*; extra == "dev"
Requires-Dist: twine==6.1.*; extra == "dev"
Dynamic: license-file
